MANIFEST.in
setup.py
test_task/__init__.py
test_task/mbox.py
test_task.egg-info/PKG-INFO
test_task.egg-info/SOURCES.txt
test_task.egg-info/dependency_links.txt
test_task.egg-info/not-zip-safe
test_task.egg-info/top_level.txt
test_task/lib/__init__.py
test_task/lib/mbox_globals.py
test_task/lib/mbox_object.py
test_task/media/__init__.py
test_task/media/fonts/__init__.py
test_task/media/icons/__init__.py
test_task/media/ui/__init__.py