Metadata-Version: 1.1
Name: test-task
Version: 0.0.5
Summary: Package prepared as barebone skeleton for an application
Home-page: https://github.com/timmwagener
Author: Timm Wagener
Author-email: wagenertimm@gmail.com
License: MIT
Keywords: Python Package Skeleton
Platform: UNKNOWN
Classifier: Programming Language :: Python
